sentinalmon/__init__.py
sentinalmon/collectors/__init__.py
sentinalmon/collectors/base.py
sentinalmon/exporter/__init__.py
sentinalmon/exporter/collectors/__init__.py
sentinalmon/exporter/collectors/cpu.py
sentinalmon/exporter/collectors/memory.py
sentinalmon/exporter/collectors/network.py
sentinalmon/exporter/collectors/storage.py
sentinalmon/exporter/server.py
sentinalmon/main.py
sentinalmon/master/__init__.py
sentinalmon/master/collectors/__init__.py
sentinalmon/master/collectors/base.py
sentinalmon/master/server.py
sentinalmon/models/__init__.py
sentinalmon/models/metrics.py
sentinalmon/models/server.py
sentinalmon/ui/__init__.py
sentinalmon/ui/main.py
sentinalmon/ui/main.tcss
sentinalmon/ui/master_client.py
sentinalmon/ui/views/__init__.py
sentinalmon/ui/views/cpu.py
sentinalmon/ui/views/memory.py
sentinalmon/ui/views/network.py
sentinalmon/ui/views/storage.py
sentinalmon/utils.py
sentinalmon-0.1.0.dist-info/METADATA
sentinalmon-0.1.0.dist-info/WHEEL
sentinalmon-0.1.0.dist-info/entry_points.txt
sentinalmon-0.1.0.dist-info/RECORD
