Metadata-Version: 2.1
Name: sentinalmon
Version: 0.1.0
Summary: 
Author: bdizen
Author-email: bdizenweb@gmail.com
Requires-Python: >=3.10,<4.0
Classifier: Programming Language :: Python :: 3
Classifier: Programming Language :: Python :: 3.10
Classifier: Programming Language :: Python :: 3.11
Classifier: Programming Language :: Python :: 3.12
Requires-Dist: fastapi (>=0.115.8,<0.116.0)
Requires-Dist: httpx (>=0.28.1,<0.29.0)
Requires-Dist: passlib (>=1.7.4,<2.0.0)
Requires-Dist: psutil (>=7.0.0,<8.0.0)
Requires-Dist: python-jose (>=3.4.0,<4.0.0)
Requires-Dist: requests (>=2.32.3,<3.0.0)
Requires-Dist: textual (>=2.1.1,<3.0.0)
Requires-Dist: typer (>=0.15.1,<0.16.0)
Requires-Dist: uvicorn (>=0.34.0,<0.35.0)
